{
  "_class": "shapePath",
  "booleanOperation": -1,
  "clippingMaskMode": 0,
  "do_objectID": "BFA6B052-3D76-4887-B7C6-12B9794997E6",
  "edited": true,
  "exportOptions": {
    "_class": "exportOptions",
    "do_objectID": "F3F2E080-9947-477F-8003-173FB8242F16",
    "exportFormats": [
    ],
    "includedLayerIds": [
    ],
    "layerOptions": 0,
    "shouldTrim": false
  },
  "frame": {
    "_class": "rect",
    "constrainProportions": false,
    "do_objectID": "E09E25C1-098A-4C0F-BD7C-3F3CE2F8A0AE",
    "height": 7.683158067158084,
    "width": 9.654983233532935,
    "x": 9.466772574850244,
    "y": 1.34736117936119
  },
  "hasClippingMask": false,
  "isClosed": true,
  "isFixedToViewport": false,
  "isFlippedHorizontal": false,
  "isFlippedVertical": false,
  "isLocked": false,
  "isVisible": true,
  "layerListExpandedType": 0,
  "name": "path3048",
  "nameIsFixed": false,
  "pointRadiusBehaviour": 1,
  "points": [
    {
      "_class": "curvePoint",
      "cornerRadius": 0,
      "curveFrom": "{0, 1}",
      "curveMode": 1,
      "curveTo": "{0, 1}",
      "hasCurveFrom": false,
      "hasCurveTo": false,
      "point": "{0, 1}"
    },
    {
      "_class": "curvePoint",
      "cornerRadius": 0,
      "curveFrom": "{0, 1.9389862843325711e-15}",
      "curveMode": 1,
      "curveTo": "{0, 1.9389862843325711e-15}",
      "hasCurveFrom": false,
      "hasCurveTo": false,
      "point": "{0, 1.9389862843325711e-15}"
    },
    {
      "_class": "curvePoint",
      "cornerRadius": 0,
      "curveFrom": "{0.31833515031361675, 0.0014778593978396939}",
      "curveMode": 1,
      "curveTo": "{0.31833515031361675, 0.0014778593978396939}",
      "hasCurveFrom": false,
      "hasCurveTo": false,
      "point": "{0.31833515031361675, 0.0014778593978396939}"
    },
    {
      "_class": "curvePoint",
      "cornerRadius": 0,
      "curveFrom": "{0.50348969369669316, 0.64621427511550733}",
      "curveMode": 1,
      "curveTo": "{0.50348969369669316, 0.64621427511550733}",
      "hasCurveFrom": false,
      "hasCurveTo": false,
      "point": "{0.50348969369669316, 0.64621427511550733}"
    },
    {
      "_class": "curvePoint",
      "cornerRadius": 0,
      "curveFrom": "{0.68421055504085826, 0}",
      "curveMode": 1,
      "curveTo": "{0.68421055504085826, 0}",
      "hasCurveFrom": false,
      "hasCurveTo": false,
      "point": "{0.68421055504085826, 0}"
    },
    {
      "_class": "curvePoint",
      "cornerRadius": 0,
      "curveFrom": "{1, 0}",
      "curveMode": 1,
      "curveTo": "{1, 0}",
      "hasCurveFrom": false,
      "hasCurveTo": false,
      "point": "{1, 0}"
    },
    {
      "_class": "curvePoint",
      "cornerRadius": 0,
      "curveFrom": "{1, 0.99999999999999811}",
      "curveMode": 1,
      "curveTo": "{1, 0.99999999999999811}",
      "hasCurveFrom": false,
      "hasCurveTo": false,
      "point": "{1, 0.99999999999999811}"
    },
    {
      "_class": "curvePoint",
      "cornerRadius": 0,
      "curveFrom": "{0.80000000000000004, 0.99999999999999811}",
      "curveMode": 1,
      "curveTo": "{0.80000000000000004, 0.99999999999999811}",
      "hasCurveFrom": false,
      "hasCurveTo": false,
      "point": "{0.80000000000000004, 0.99999999999999811}"
    },
    {
      "_class": "curvePoint",
      "cornerRadius": 0,
      "curveFrom": "{0.80000000000000004, 0.2631578947368427}",
      "curveMode": 1,
      "curveTo": "{0.80000000000000004, 0.2631578947368427}",
      "hasCurveFrom": false,
      "hasCurveTo": false,
      "point": "{0.80000000000000004, 0.2631578947368427}"
    },
    {
      "_class": "curvePoint",
      "cornerRadius": 0,
      "curveFrom": "{0.58799578660692231, 0.99999999999999811}",
      "curveMode": 1,
      "curveTo": "{0.58799578660692231, 0.99999999999999811}",
      "hasCurveFrom": false,
      "hasCurveTo": false,
      "point": "{0.58799578660692231, 0.99999999999999811}"
    },
    {
      "_class": "curvePoint",
      "cornerRadius": 0,
      "curveFrom": "{0.41259535735385794, 0.99999999999999811}",
      "curveMode": 1,
      "curveTo": "{0.41259535735385794, 0.99999999999999811}",
      "hasCurveFrom": false,
      "hasCurveTo": false,
      "point": "{0.41259535735385794, 0.99999999999999811}"
    },
    {
      "_class": "curvePoint",
      "cornerRadius": 0,
      "curveFrom": "{0.19999999999999973, 0.2631578947368427}",
      "curveMode": 1,
      "curveTo": "{0.19999999999999973, 0.2631578947368427}",
      "hasCurveFrom": false,
      "hasCurveTo": false,
      "point": "{0.19999999999999973, 0.2631578947368427}"
    },
    {
      "_class": "curvePoint",
      "cornerRadius": 0,
      "curveFrom": "{0.19999999999999973, 0.99999999999999811}",
      "curveMode": 1,
      "curveTo": "{0.19999999999999973, 0.99999999999999811}",
      "hasCurveFrom": false,
      "hasCurveTo": false,
      "point": "{0.19999999999999973, 0.99999999999999811}"
    }
  ],
  "resizingConstraint": 63,
  "resizingType": 0,
  "rotation": 0,
  "shouldBreakMaskChain": false,
  "style": {
    "_class": "style",
    "blur": {
      "_class": "blur",
      "center": "{0.5, 0.5}",
      "do_objectID": "CAB2A490-A9ED-4CC6-AFBC-49F24CD49CB8",
      "isEnabled": false,
      "motionAngle": 0,
      "radius": 0.6586826347305389,
      "saturation": 1,
      "type": 0
    },
    "do_objectID": "4C851113-7345-4FF8-B612-A5BC9D1BF79A",
    "endMarkerType": 0,
    "fills": [
      {
        "_class": "fill",
        "color": {
          "_class": "color",
          "alpha": 1,
          "blue": 0.8156862745098039,
          "green": 0.4352941176470588,
          "red": 0.00392156862745098
        },
        "fillType": 0,
        "isEnabled": true,
        "noiseIndex": 0,
        "noiseIntensity": 0,
        "patternFillType": 1,
        "patternTileScale": 1
      }
    ],
    "miterLimit": 10,
    "startMarkerType": 0,
    "windingRule": 1
  }
}